actions_lib/__init__.py
actions_lib/combine.py
actions_lib/json_reader.py
actions_lib/actions/__init__.py
actions_lib/actions/ai.json
actions_lib/actions/consts.py
actions_lib/actions/type.py
actions_lib/actions/contact/__init__.py
actions_lib/actions/contact/ai.json
actions_lib/actions/contact/config.json
actions_lib/actions/contact/contact.py
actions_lib/actions/setting/ai.json
actions_lib/actions/transfer/README.md
actions_lib/actions/transfer/__init__.py
actions_lib/actions/transfer/ai.json
actions_lib/actions/transfer/config.json
actions_lib/actions/transfer/transfer.py
actions_lib/actions/user/__init__.py
actions_lib/actions/user/ai.json
actions_lib/actions/user/user.py
actions_lib/utils/__init__.py
actions_lib/utils/contact_tool.py
actions_lib-0.1.123.dist-info/LICENSE
actions_lib-0.1.123.dist-info/METADATA
actions_lib-0.1.123.dist-info/WHEEL
actions_lib-0.1.123.dist-info/top_level.txt
actions_lib-0.1.123.dist-info/RECORD
